gradioWrapper/__init__.py
gradioWrapper/compiler.py
gradioWrapper-0.0.7.dist-info/LICENSE
gradioWrapper-0.0.7.dist-info/METADATA
gradioWrapper-0.0.7.dist-info/WHEEL
gradioWrapper-0.0.7.dist-info/top_level.txt
gradioWrapper-0.0.7.dist-info/RECORD
