Metadata-Version: 2.1
Name: gradioWrapper
Version: 0.0.7
Summary: A basic gradio class, class function, and functional decorator
Home-page: https://github.com/LVivona/GradioWrapper
Author: Luca Vivona
License: UNKNOWN
Keywords: python,sockets,artificial intelligence,machine learning,visualization,wrapper,decorator,testing
Platform: UNKNOWN
Classifier: Development Status :: 1 - Planning
Classifier: Intended Audience :: Developers
Classifier: Programming Language :: Python :: 3
Classifier: Operating System :: Unix
Classifier: Operating System :: MacOS :: MacOS X
Classifier: Operating System :: Microsoft :: Windows
License-File: LICENSE
Requires-Dist: gradio
